mcp_agent/__init__.py
mcp_agent/app.py
mcp_agent/config.py
mcp_agent/console.py
mcp_agent/py.typed
mcp_agent/agents/__init__.py
mcp_agent/agents/agent.py
mcp_agent/agents/agent_spec.py
mcp_agent/cli/README.md
mcp_agent/cli/__init__.py
mcp_agent/cli/__main__.py
mcp_agent/cli/exceptions.py
mcp_agent/cli/main.py
mcp_agent/cli/main_bootstrap.py
mcp_agent/cli/auth/__init__.py
mcp_agent/cli/auth/constants.py
mcp_agent/cli/auth/main.py
mcp_agent/cli/auth/models.py
mcp_agent/cli/cloud/__init__.py
mcp_agent/cli/cloud/main.py
mcp_agent/cli/cloud/commands/__init__.py
mcp_agent/cli/cloud/commands/utils.py
mcp_agent/cli/cloud/commands/app/__init__.py
mcp_agent/cli/cloud/commands/app/delete/__init__.py
mcp_agent/cli/cloud/commands/app/delete/main.py
mcp_agent/cli/cloud/commands/app/status/__init__.py
mcp_agent/cli/cloud/commands/app/status/main.py
mcp_agent/cli/cloud/commands/app/workflows/__init__.py
mcp_agent/cli/cloud/commands/app/workflows/main.py
mcp_agent/cli/cloud/commands/apps/__init__.py
mcp_agent/cli/cloud/commands/apps/list/__init__.py
mcp_agent/cli/cloud/commands/apps/list/main.py
mcp_agent/cli/cloud/commands/apps/update/__init__.py
mcp_agent/cli/cloud/commands/apps/update/main.py
mcp_agent/cli/cloud/commands/auth/__init__.py
mcp_agent/cli/cloud/commands/auth/login/__init__.py
mcp_agent/cli/cloud/commands/auth/login/constants.py
mcp_agent/cli/cloud/commands/auth/login/main.py
mcp_agent/cli/cloud/commands/auth/logout/__init__.py
mcp_agent/cli/cloud/commands/auth/logout/main.py
mcp_agent/cli/cloud/commands/auth/whoami/__init__.py
mcp_agent/cli/cloud/commands/auth/whoami/main.py
mcp_agent/cli/cloud/commands/configure/__init__.py
mcp_agent/cli/cloud/commands/configure/main.py
mcp_agent/cli/cloud/commands/deploy/__init__.py
mcp_agent/cli/cloud/commands/deploy/bundle_utils.py
mcp_agent/cli/cloud/commands/deploy/constants.py
mcp_agent/cli/cloud/commands/deploy/main.py
mcp_agent/cli/cloud/commands/deploy/materialize.py
mcp_agent/cli/cloud/commands/deploy/settings.py
mcp_agent-0.2.6.dist-info/METADATA
mcp_agent-0.2.6.dist-info/WHEEL
mcp_agent-0.2.6.dist-info/entry_points.txt
mcp_agent-0.2.6.dist-info/licenses/LICENSE
mcp_agent-0.2.6.dist-info/RECORD
