Metadata-Version: 2.4
Name: mcp-agent
Version: 0.2.6
Summary: Build effective agents with Model Context Protocol (MCP) using simple, composable patterns.
Author-email: Sarmad Qadri <sarmad@lastmileai.dev>
License:                                  Apache License
License-File: LICENSE
Classifier: License :: OSI Approved :: Apache Software License
Classifier: Operating System :: OS Independent
Classifier: Programming Language :: Python :: 3
Requires-Python: >=3.10
Requires-Dist: aiohttp>=3.11.13
Requires-Dist: fastapi>=0.115.6
Requires-Dist: httpx>=0.28.1
Requires-Dist: jsonref>=1.1.0
Requires-Dist: mcp>=1.20.0
Requires-Dist: numpy>=2.1.3
Requires-Dist: opentelemetry-distro>=0.50b0
Requires-Dist: opentelemetry-exporter-otlp-proto-http>=1.29.0
Requires-Dist: opentelemetry-instrumentation-anthropic>=0.39.3
Requires-Dist: opentelemetry-instrumentation-openai>=0.39.3
Requires-Dist: pathspec>=0.12.1
Requires-Dist: prompt-toolkit>=3.0.50
Requires-Dist: pydantic-settings>=2.7.0
Requires-Dist: pydantic-yaml>=1.5.1
Requires-Dist: pydantic>=2.10.4
Requires-Dist: python-dotenv>=1.0.0
Requires-Dist: pyyaml>=6.0.2
Requires-Dist: rich>=13.9.4
Requires-Dist: scikit-learn>=1.6.0
Requires-Dist: typer>=0.15.3
Requires-Dist: watchdog>=6.0.0
Requires-Dist: websockets>=12.0
Provides-Extra: anthropic
Requires-Dist: anthropic>=0.48.0; extra == 'anthropic'
Provides-Extra: anthropic-bedrock
Requires-Dist: anthropic[bedrock]>=0.52.0; extra == 'anthropic-bedrock'
Provides-Extra: anthropic-vertex
Requires-Dist: anthropic[vertex]>=0.52.0; extra == 'anthropic-vertex'
Requires-Dist: google-cloud-aiplatform>=1.101.0; extra == 'anthropic-vertex'
Provides-Extra: azure
Requires-Dist: azure-ai-inference>=1.0.0b9; extra == 'azure'
Requires-Dist: azure-identity>=1.22.0; extra == 'azure'
Provides-Extra: bedrock
Requires-Dist: boto3>=1.37.23; extra == 'bedrock'
Provides-Extra: cohere
Requires-Dist: cohere>=5.13.4; extra == 'cohere'
Provides-Extra: crewai
Requires-Dist: crewai>=0.126.0; extra == 'crewai'
Provides-Extra: google
Requires-Dist: google-genai>=1.10.0; extra == 'google'
Provides-Extra: langchain
Requires-Dist: langchain-core>=0.3.64; extra == 'langchain'
Provides-Extra: openai
Requires-Dist: openai>=1.58.1; extra == 'openai'
Provides-Extra: redis
Requires-Dist: redis[hiredis]>=5.0.4; extra == 'redis'
Provides-Extra: temporal
Requires-Dist: temporalio[opentelemetry]>=1.10.0; extra == 'temporal'
